hopeit_agents/mcp_client/__init__.py
hopeit_agents/mcp_client/client.py
hopeit_agents/mcp_client/models.py
hopeit_agents/mcp_client/py.typed
hopeit_agents/mcp_client/settings.py
hopeit_agents/mcp_client/api/__init__.py
hopeit_agents/mcp_client/api/invoke_tool.py
hopeit_agents/mcp_client/api/list_tools.py
hopeit_agents/mcp_client/api/py.typed
hopeit_agents_mcp_client-0.1.0b2.dist-info/METADATA
hopeit_agents_mcp_client-0.1.0b2.dist-info/WHEEL
hopeit_agents_mcp_client-0.1.0b2.dist-info/top_level.txt
hopeit_agents_mcp_client-0.1.0b2.dist-info/RECORD
